md2_notfresh-0.0.4.data/data/my_data/data_file
md_helper/__init__.py
md_helper/md_add_space.py
md_helper/md_update_url.py
md_helper/question_list.py
md_helper/standard-readme-django-cn.template
md_helper/templite.py
sample/__init__.py
sample/package_data.dat
sample/simple.py
md2_notfresh-0.0.4.dist-info/LICENSE.txt
md2_notfresh-0.0.4.dist-info/METADATA
md2_notfresh-0.0.4.dist-info/WHEEL
md2_notfresh-0.0.4.dist-info/entry_points.txt
md2_notfresh-0.0.4.dist-info/top_level.txt
md2_notfresh-0.0.4.dist-info/RECORD
